scripts/replay_pcap_file.sh
scripts/suricata_log_bash_auto_complete.sh
suricatalog/__init__.py
suricatalog/alert_apps.py
suricatalog/canned.py
suricatalog/clipboard.py
suricatalog/filter.py
suricatalog/flow_app.py
suricatalog/hostdatause_app.py
suricatalog/log.py
suricatalog/oneshot_app.py
suricatalog/payload_app.py
suricatalog/providers.py
suricatalog/report.py
suricatalog/screens.py
suricatalog/time.py
suricatalog/topuser_app.py
suricatalog/css/alert.tcss
suricatalog/css/canned.tcss
suricatalog/css/details_screen.tcss
suricatalog/css/error_screen.tcss
suricatalog/scripts/__init__.py
suricatalog/scripts/eve_autocomplete.py
suricatalog/scripts/eve_json.py
suricatalog/scripts/eve_log.py
suricatalog/scripts/eve_payload.py
suricatalog/scripts/eve_server.py
suricatalog-1.1.3.data/scripts/replay_pcap_file.sh
suricatalog-1.1.3.data/scripts/suricata_log_bash_auto_complete.sh
suricatalog-1.1.3.dist-info/METADATA
suricatalog-1.1.3.dist-info/WHEEL
suricatalog-1.1.3.dist-info/entry_points.txt
suricatalog-1.1.3.dist-info/top_level.txt
suricatalog-1.1.3.dist-info/RECORD
