Metadata-Version: 2.4
Name: SuricataLog
Version: 1.1.3
Summary: Scripts to display contents of Suricata eve.json log
Author-email: Jose Vicente Nunez <kodegeek.com@protonmail.com>
Maintainer-email: Jose Vicente Nunez <kodegeek.com@protonmail.com>
License-Expression: MIT AND (Apache-2.0 OR BSD-2-Clause)
Project-URL: Repository, https://github.com/josevnz/SuricataLog
Keywords: suricata,log,eve,json,cybersecurity
Classifier: Development Status :: 5 - Production/Stable
Classifier: Programming Language :: Python
Requires-Python: >=3.11
Requires-Dist: textual==3.4.0
Requires-Dist: textual-serve==1.1.1
Requires-Dist: pytz==2025.2
Requires-Dist: pyperclip==1.9.0
Requires-Dist: orjson==3.10.16
Provides-Extra: lint
Requires-Dist: ruff==0.12.0; extra == "lint"
Provides-Extra: dev
Requires-Dist: textual-dev==1.7.0; extra == "dev"
Requires-Dist: twine>=6.1.0; extra == "dev"
Requires-Dist: build>=1.2.1; extra == "dev"
